{
    "case_number": 20,
    "case_name": "PP_0019YSY",
    "group_name": "A.3.1",
    "number_of_sequences": 1992,
    "number_of_changes": 72,
    "best_candidates": "A.2.1.1 + A.3.1 + A.2.1.1",
    "best_candidates_breakpoints_target": "27-28, 38-39",
    "best_candidates_breakpoints_genomic": "5110 - 5111, 5283 - 5284",
    "direction_L1": "<<",
    "initial_region_span": "1-27,36-38,39-72",
    "gap_history": "27-39 -> 27-36",
    "alternative_candidates": "[], []",
    "model_comparison": "2BP vs 1BP: 8.24e-21",
    "p_value_vs_L1": "1.24e-21",
    "p_value_vs_L2": "2.96e-75",
    "flags": "Model_2BP_Best"
}