{
    "case_number": 79,
    "case_name": "OR146424.1",
    "group_name": "B.1.17.NmC3",
    "number_of_sequences": 53,
    "number_of_changes": 58,
    "best_candidates": "B.1.17.NmC3 + B.1.NmC6 + B.1.17.NmC3",
    "best_candidates_breakpoints_target": "50-51, 53-54",
    "best_candidates_breakpoints_genomic": "150549 - 150550, 157300 - 157301",
    "direction_L1": ">>",
    "initial_region_span": "1-50,51-53,54-58",
    "gap_history": "50-54 -> ",
    "alternative_candidates": "[], []",
    "model_comparison": "2BP vs 1BP: 3.15e-01",
    "p_value_vs_L1": "5.17e-13",
    "p_value_vs_L2": "8.14e-80",
    "flags": "Model_2BP_Best"
}