{
    "case_number": 3,
    "case_name": "PV307768.1",
    "group_name": "A.1.NmC12",
    "number_of_sequences": 640,
    "number_of_changes": 160,
    "best_candidates": "A.1.NmC12 + A.1.NmC10 + A.1.NmC12",
    "best_candidates_breakpoints_target": "104-105, 107-108",
    "best_candidates_breakpoints_genomic": "1043 - 1044, 1061 - 1062",
    "direction_L1": ">>",
    "initial_region_span": "1-104,105-107,108-160",
    "gap_history": "104-108 -> ",
    "alternative_candidates": "[], []",
    "model_comparison": "2BP vs 1BP: 2.76e-08",
    "p_value_vs_L1": "2.19e-17",
    "p_value_vs_L2": "3.66e-82",
    "flags": "Model_2BP_Best"
}