{
    "case_number": 40,
    "case_name": "PP_001BAG3",
    "group_name": "A.D.4.NmC1",
    "number_of_sequences": 2189,
    "number_of_changes": 61,
    "best_candidates": "A.D.4.NmC3 + A.D.4.NmC1",
    "best_candidates_breakpoints_target": "13-14",
    "best_candidates_breakpoints_genomic": "4959 - 4960",
    "direction_L1": "<<",
    "initial_region_span": "1-13,14-61",
    "gap_history": "",
    "alternative_candidates": "[], []",
    "model_comparison": "-",
    "p_value_vs_L1": "8.09e-08",
    "p_value_vs_L2": "1.23e-07",
    "flags": "Model_2BP_Bad_L1_opp"
}