{
    "case_number": 47,
    "case_name": "PP_001LZ4K",
    "group_name": "A.D.NmC1",
    "number_of_sequences": 515,
    "number_of_changes": 19,
    "best_candidates": "A.D.3.6 + A.D.NmC1",
    "best_candidates_breakpoints_target": "6-7",
    "best_candidates_breakpoints_genomic": "5407 - 5408",
    "direction_L1": "<<",
    "initial_region_span": "1-6,7-19",
    "gap_history": "",
    "alternative_candidates": "[], []",
    "model_comparison": "-",
    "p_value_vs_L1": "2.13e-25",
    "p_value_vs_L2": "1.19e-03",
    "flags": "Model_2BP_Bad_L1_opp"
}