{
    "case_number": 8,
    "case_name": "PP_002RT4E",
    "group_name": "B.D.1",
    "number_of_sequences": 334,
    "number_of_changes": 29,
    "best_candidates": "B.D.1 + B.D.E.2",
    "best_candidates_breakpoints_target": "9-10",
    "best_candidates_breakpoints_genomic": "5309 - 5310",
    "direction_L1": "<<",
    "initial_region_span": "1-6,10-29",
    "gap_history": "6-10",
    "alternative_candidates": "[], []",
    "model_comparison": "-",
    "p_value_vs_L1": "2.11e-09",
    "p_value_vs_L2": "5.99e-04",
    "flags": "Model_2BP_Bad_L1_opp"
}