{
    "case_number": 9,
    "case_name": "PV319256.1",
    "group_name": "A.1.NmC13",
    "number_of_sequences": 668,
    "number_of_changes": 153,
    "best_candidates": "A.1.NmC13 + A.1.NmC5 + A.1.NmC13",
    "best_candidates_breakpoints_target": "10-11, 12-13",
    "best_candidates_breakpoints_genomic": "143 - 144, 194 - 195",
    "direction_L1": "<<",
    "initial_region_span": "1-9,11-12,13-153",
    "gap_history": "9-13 -> 9-11",
    "alternative_candidates": "[], []",
    "model_comparison": "2BP vs 1BP: 7.91e-01",
    "p_value_vs_L1": "2.33e+00",
    "p_value_vs_L2": "2.05e-144",
    "flags": "Model_2BP_Best"
}