{
    "case_number": 53,
    "case_name": "OP680502.1",
    "group_name": "B.1",
    "number_of_sequences": 452,
    "number_of_changes": 60,
    "best_candidates": "B.1.6 + B.1.NmC5",
    "best_candidates_breakpoints_target": "51-52",
    "best_candidates_breakpoints_genomic": "157300 - 157301",
    "direction_L1": ">>",
    "initial_region_span": "1-51,52-60",
    "gap_history": "",
    "alternative_candidates": "[], []",
    "model_comparison": "-",
    "p_value_vs_L1": "3.34e-10",
    "p_value_vs_L2": "2.66e-25",
    "flags": "Model_2BP_Bad_L1_opp"
}