{
    "case_number": 8,
    "case_name": "PP_001DW8V",
    "group_name": "A.D.4.NmC3",
    "number_of_sequences": 1653,
    "number_of_changes": 65,
    "best_candidates": "A.D.4.NmC3 + A.D.2.2.NmC1",
    "best_candidates_breakpoints_target": "62-63",
    "best_candidates_breakpoints_genomic": "5543 - 5544",
    "direction_L1": ">>",
    "initial_region_span": "1-62,63-65",
    "gap_history": "",
    "alternative_candidates": "[], []",
    "model_comparison": "-",
    "p_value_vs_L1": "6.30e-02",
    "p_value_vs_L2": "1.93e-293",
    "flags": "Model_2BP_Bad_L1_opp"
}