{
    "case_number": 40,
    "case_name": "PP_001ABKX",
    "group_name": "A.D.4.NmC1",
    "number_of_sequences": 2189,
    "number_of_changes": 61,
    "best_candidates": "A.D.4.NmC3 + A.3.1.NmC1",
    "best_candidates_breakpoints_target": "56-57",
    "best_candidates_breakpoints_genomic": "5533 - 5534",
    "direction_L1": ">>",
    "initial_region_span": "1-56,57-61",
    "gap_history": "",
    "alternative_candidates": "[], []",
    "model_comparison": "-",
    "p_value_vs_L1": "3.20e-03",
    "p_value_vs_L2": "1.75e-318",
    "flags": "Model_2BP_Bad_L1_opp"
}