{
    "case_number": 10,
    "case_name": "OQ982396.1",
    "group_name": "A.1.NmC4",
    "number_of_sequences": 1744,
    "number_of_changes": 160,
    "best_candidates": "A.1.NmC7 + A.1.NmC4",
    "best_candidates_breakpoints_target": "6-7",
    "best_candidates_breakpoints_genomic": "53 - 54",
    "direction_L1": "<<",
    "initial_region_span": "1-5,9-160",
    "gap_history": "5-9",
    "alternative_candidates": "[], []",
    "model_comparison": "-",
    "p_value_vs_L1": "5.83e-63",
    "p_value_vs_L2": "8.52e+05",
    "flags": "Model_2BP_Bad_L1_opp"
}